aiotraq_bot/__init__.py
aiotraq_bot/bot.py
aiotraq_bot/models/__init__.py
aiotraq_bot/models/common.py
aiotraq_bot/models/event.py
aiotraq_bot/models/event_models.py
aiotraq_bot/py.typed
aiotraq_bot-0.2.5.dist-info/METADATA
aiotraq_bot-0.2.5.dist-info/WHEEL
aiotraq_bot-0.2.5.dist-info/RECORD
