Metadata-Version: 2.1
Name: aiotraq-bot
Version: 0.2.5
Summary: Async ready traQ Bot library
Home-page: https://github.com/toshi-pono/aiotraq
License: MIT
Keywords: traQ,bot,async,aiotraq
Author: toshi00
Requires-Python: >=3.10,<4.0
Classifier: License :: OSI Approved :: MIT License
Classifier: Programming Language :: Python :: 3
Classifier: Programming Language :: Python :: 3.10
Classifier: Programming Language :: Python :: 3.11
Classifier: Programming Language :: Python :: 3.12
Requires-Dist: fastapi (>=0.100.0)
Requires-Dist: uvicorn[standard] (>=0.12.0)
Project-URL: Repository, https://github.com/toshi-pono/aiotraq
Project-URL: Source Code, https://github.com/toshi-pono/aiotraq/tree/main/libs/bot
